{
  "generatedAt": "2026-05-20T15:54:29.857Z",
  "source": "yahoo-finance-chart",
  "successCount": 6,
  "staleCount": 0,
  "errorMessage": "",
  "records": [
    {
      "key": "gift-nifty",
      "label": "GIFT NIFTY(NIFTY NSE)",
      "quoteUrl": "https://query1.finance.yahoo.com/v8/finance/chart/%5ENSEI?range=1d&interval=1d",
      "chartUrl": "https://www.investing.com/indices/gift-nifty-50-c1-futures-chart",
      "current": 23659,
      "previousClose": 23618,
      "change": 41,
      "pct": 0.17359640951816413,
      "sentiment": "Mild Bullish",
      "trendGroup": "bullish",
      "arrow": "↑",
      "isAvailable": true,
      "isStale": false,
      "fetchedAt": "2026-05-20T15:54:29.857Z",
      "errorMessage": ""
    },
    {
      "key": "sp500",
      "label": "S&P 500",
      "quoteUrl": "https://query1.finance.yahoo.com/v8/finance/chart/%5EGSPC?range=1d&interval=1d",
      "chartUrl": "https://www.investing.com/indices/us-spx-500-chart",
      "current": 7424.87,
      "previousClose": 7353.61,
      "change": 71.26000000000022,
      "pct": 0.9690478554070752,
      "sentiment": "Strong Bullish",
      "trendGroup": "bullish",
      "arrow": "↑",
      "isAvailable": true,
      "isStale": false,
      "fetchedAt": "2026-05-20T15:54:29.857Z",
      "errorMessage": ""
    },
    {
      "key": "nasdaq",
      "label": "Nasdaq Composite",
      "quoteUrl": "https://query1.finance.yahoo.com/v8/finance/chart/%5EIXIC?range=1d&interval=1d",
      "chartUrl": "https://www.investing.com/indices/nasdaq-composite-chart",
      "current": 26223.154,
      "previousClose": 25870.709,
      "change": 352.4449999999997,
      "pct": 1.362332203574319,
      "sentiment": "Strong Bullish",
      "trendGroup": "bullish",
      "arrow": "↑",
      "isAvailable": true,
      "isStale": false,
      "fetchedAt": "2026-05-20T15:54:29.857Z",
      "errorMessage": ""
    },
    {
      "key": "nikkei",
      "label": "Nikkei 225",
      "quoteUrl": "https://query1.finance.yahoo.com/v8/finance/chart/%5EN225?range=1d&interval=1d",
      "chartUrl": "https://www.investing.com/indices/japan-ni225-chart",
      "current": 59804.41,
      "previousClose": 60550.59,
      "change": -746.179999999993,
      "pct": -1.2323249038531137,
      "sentiment": "Strong Bearish",
      "trendGroup": "bearish",
      "arrow": "↓",
      "isAvailable": true,
      "isStale": false,
      "fetchedAt": "2026-05-20T15:54:29.857Z",
      "errorMessage": ""
    },
    {
      "key": "hang-seng",
      "label": "Hang Seng",
      "quoteUrl": "https://query1.finance.yahoo.com/v8/finance/chart/%5EHSI?range=1d&interval=1d",
      "chartUrl": "https://www.investing.com/indices/hang-sen-40-chart",
      "current": 25651.12,
      "previousClose": 25797.85,
      "change": -146.72999999999956,
      "pct": -0.5687683275931893,
      "sentiment": "Strong Bearish",
      "trendGroup": "bearish",
      "arrow": "↓",
      "isAvailable": true,
      "isStale": false,
      "fetchedAt": "2026-05-20T15:54:29.857Z",
      "errorMessage": ""
    },
    {
      "key": "crude-oil",
      "label": "Crude Oil (WTI)",
      "quoteUrl": "https://query1.finance.yahoo.com/v8/finance/chart/CL=F?range=1d&interval=1d",
      "chartUrl": "https://www.investing.com/commodities/crude-oil-streaming-chart",
      "current": 99.08,
      "previousClose": 104.15,
      "change": -5.070000000000007,
      "pct": -4.867978876620266,
      "sentiment": "Strong Bearish",
      "trendGroup": "bearish",
      "arrow": "↓",
      "isAvailable": true,
      "isStale": false,
      "fetchedAt": "2026-05-20T15:54:29.857Z",
      "errorMessage": ""
    }
  ]
}
